[
  {
    "_id": "dish_1",
    "restaurant_id": "rest_1",
    "name": "Coddled pork with cider",
    "description": "STEP 1\r\nHeat the butter in a casserole dish until sizzling, then fry the pork for 2-3 mins on each side until browned. Remove from the pan.\r\n\r\nSTEP 2\r\nTip the bacon, carrot, potatoes and swede into the pan, then gently fry until slightly co",
    "price": 22.97,
    "ingredients": [
      "Butter",
      "Pork Chops",
      "Bacon",
      "Potatoes",
      "Carrots",
      "Swede",
      "Cabbage",
      "Bay Leaf",
      "Cider",
      "Chicken Stock"
    ]
  },
  {
    "_id": "dish_2",
    "restaurant_id": "rest_1",
    "name": "Pizza Express Margherita",
    "description": "1 Preheat the oven to 230\u00b0C.\r\n\r\n2 Add the sugar and crumble the fresh yeast into warm water.\r\n\r\n3 Allow the mixture to stand for 10 \u2013 15 minutes in a warm place (we find a windowsill on a sunny day works best) until froth develops on the su",
    "price": 15.99,
    "ingredients": [
      "Water",
      "Sugar",
      "Yeast",
      "Plain Flour",
      "Salt",
      "Olive Oil",
      "Passata",
      "Mozzarella",
      "Oregano",
      "Basil",
      "Black Pepper"
    ]
  },
  {
    "_id": "dish_3",
    "restaurant_id": "rest_1",
    "name": "Bread and Butter Pudding",
    "description": "Grease a 1 litre/2 pint pie dish with butter.\r\nCut the crusts off the bread. Spread each slice with on one side with butter, then cut into triangles.\r\nArrange a layer of bread, buttered-side up, in the bottom of the dish, then add a layer o",
    "price": 20.02,
    "ingredients": [
      "butter",
      "bread",
      "sultanas",
      "cinnamon",
      "milk",
      "double cream",
      "eggs",
      "sugar",
      "nutmeg"
    ]
  },
  {
    "_id": "dish_4",
    "restaurant_id": "rest_1",
    "name": "Honey Yogurt Cheesecake",
    "description": "Heat oven to 160C/140C fan/gas 3. Crush the biscuits and most of the almonds inside a plastic food bag using a rolling pin. Mix with the butter, then press into the bottom of a deep, oval, 23cm dish (or something similar in size \u2013 a roastin",
    "price": 16.39,
    "ingredients": [
      "Digestive Biscuits",
      "Almonds",
      "Butter",
      "Greek Yogurt",
      "Mascarpone",
      "Eggs",
      "Lemon",
      "Orange",
      "Honey",
      "Fruit Mix"
    ]
  },
  {
    "_id": "dish_5",
    "restaurant_id": "rest_1",
    "name": "Pizza Express Margherita",
    "description": "1 Preheat the oven to 230\u00b0C.\r\n\r\n2 Add the sugar and crumble the fresh yeast into warm water.\r\n\r\n3 Allow the mixture to stand for 10 \u2013 15 minutes in a warm place (we find a windowsill on a sunny day works best) until froth develops on the su",
    "price": 25.88,
    "ingredients": [
      "Water",
      "Sugar",
      "Yeast",
      "Plain Flour",
      "Salt",
      "Olive Oil",
      "Passata",
      "Mozzarella",
      "Oregano",
      "Basil",
      "Black Pepper"
    ]
  },
  {
    "_id": "dish_6",
    "restaurant_id": "rest_1",
    "name": "Beef Sunday Roast",
    "description": "Cook the Broccoli and Carrots in a pan of boiling water until tender.\r\n\r\nRoast the Beef and Potatoes in the oven for 45mins, the potatoes may need to be checked regularly to not overcook.\r\n\r\nTo make the Yorkshire puddings:\r\nHeat oven to 230",
    "price": 22.63,
    "ingredients": [
      "Beef",
      "Broccoli",
      "Potatoes",
      "Carrots",
      "plain flour",
      "Eggs",
      "milk",
      "sunflower oil"
    ]
  },
  {
    "_id": "dish_7",
    "restaurant_id": "rest_1",
    "name": "Sledz w Oleju (Polish Herrings)",
    "description": "Soak herring in cold water for at least 1 hour. If very salty, repeat, changing the water each time.\r\n\r\nDrain thoroughly and slice herring into bite-size pieces.\r\n\r\nPlace in a jar large enough to accommodate the pieces and cover with oil, a",
    "price": 14.33,
    "ingredients": [
      "Herring",
      "Onion",
      "Olive Oil",
      "Allspice",
      "Pepper",
      "Bay Leaf"
    ]
  },
  {
    "_id": "dish_8",
    "restaurant_id": "rest_1",
    "name": "Fish Soup (Ukha)",
    "description": "In a medium pot, heat the olive oil over medium-high heat. Add the onions and cook, stirring occasionally until the onions start to caramelize. Add the carrots and cook until the carrots start to soften, about 4 more minutes.\r\nAdd the stock",
    "price": 19.8,
    "ingredients": [
      "Olive Oil",
      "Onion",
      "Carrots",
      "Fish Stock",
      "Water",
      "Potatoes",
      "Bay Leaf",
      "Cod",
      "Salmon"
    ]
  },
  {
    "_id": "dish_9",
    "restaurant_id": "rest_1",
    "name": "Rappie Pie",
    "description": "Preheat oven to 400 degrees F (200 degrees C). Grease a 10x14x2-inch baking pan.\r\nHeat margarine in a skillet over medium heat; stir in onion. Cook and stir until onion has softened and turned translucent, about 5 minutes. Reduce heat to lo",
    "price": 26.43,
    "ingredients": [
      "Butter",
      "Onions",
      "Chicken Stock",
      "Chicken Breast",
      "Potatoes",
      "Salt",
      "Black Pepper"
    ]
  },
  {
    "_id": "dish_10",
    "restaurant_id": "rest_1",
    "name": "Peanut Butter Cookies",
    "description": "Preheat oven to 350\u00baF (180\u00baC).\r\nIn a large bowl, mix together the peanut butter, sugar, and egg.\r\nScoop out a spoonful of dough and roll it into a ball. Place the cookie balls onto a nonstick baking sheet.\r\nFor extra decoration and to make ",
    "price": 22.55,
    "ingredients": [
      "Peanut Butter",
      "Sugar",
      "Egg"
    ]
  },
  {
    "_id": "dish_11",
    "restaurant_id": "rest_1",
    "name": "Snert (Dutch Split Pea Soup)",
    "description": "Gather the ingredients.\r\n\r\nIn a large soup pot, bring water, split peas, pork belly or bacon, pork chop, and bouillon cube to a boil. Reduce the heat to a simmer, cover and let cook for 45 minutes, stirring occasionally and skimming off any",
    "price": 12.88,
    "ingredients": [
      "Water",
      "Peas",
      "Pork",
      "Vegetable Stock Cube",
      "Celery",
      "Carrots",
      "Potatoes",
      "Onion",
      "Leek",
      "Celeriac",
      "Sausages"
    ]
  },
  {
    "_id": "dish_12",
    "restaurant_id": "rest_1",
    "name": "Kung Pao Chicken",
    "description": "Combine the sake or rice wine, soy sauce, sesame oil and cornflour dissolved in water. Divide mixture in half.\r\nIn a glass dish or bowl, combine half of the sake mixture with the chicken pieces and toss to coat. Cover dish and place in refr",
    "price": 14.27,
    "ingredients": [
      "Sake",
      "Soy Sauce",
      "Sesame Seed Oil",
      "Corn Flour",
      "Water",
      "Chicken",
      "Chilli Powder",
      "Rice Vinegar",
      "Brown Sugar",
      "Spring Onions",
      "Garlic Clove",
      "Water Chestnut",
      "Peanuts"
    ]
  },
  {
    "_id": "dish_13",
    "restaurant_id": "rest_1",
    "name": "Brie wrapped in prosciutto & brioche",
    "description": "Mix the flour, 1 tsp salt, caster sugar, yeast, milk and eggs together in a mixer using the dough attachment for 5 mins until the dough is smooth. Add the butter and mix for a further 4 mins on medium speed. Scrape the dough bowl and mix ag",
    "price": 25.73,
    "ingredients": [
      "Plain Flour",
      "Caster Sugar",
      "Yeast",
      "Milk",
      "Eggs",
      "Eggs",
      "Butter",
      "Brie",
      "Prosciutto"
    ]
  },
  {
    "_id": "dish_14",
    "restaurant_id": "rest_1",
    "name": "Pate Chinois",
    "description": "In a large pot of salted water, cook the potatoes until they are very tender. Drain.\r\nWith a masher, coarsely crush the potatoes with at least 30 ml (2 tablespoons) of butter. With an electric mixer, pur\u00e9e with the milk. Season with salt an",
    "price": 7.13,
    "ingredients": [
      "Potatoes",
      "Butter",
      "Milk",
      "Minced Beef",
      "Onion",
      "Creamed Corn",
      "Paprika",
      "Parsley",
      "Salt",
      "Pepper"
    ]
  },
  {
    "_id": "dish_15",
    "restaurant_id": "rest_1",
    "name": "Lamb Rogan josh",
    "description": "\r\nPut the onions in a food processor and whizz until very finely chopped. Heat the oil in a large heavy-based pan, then fry the onion with the lid on, stirring every now and then, until it is really golden and soft. Add the garlic and ginge",
    "price": 22.05,
    "ingredients": [
      "Onion",
      "Sunflower Oil",
      "Garlic",
      "Ginger",
      "Madras Paste",
      "Paprika",
      "cinnamon stick",
      "Cardamom",
      "Cloves",
      "Bay Leaf",
      "Tomato Pur\u00e9e",
      "Lamb",
      "Greek yogurt",
      "Coriander"
    ]
  },
  {
    "_id": "dish_16",
    "restaurant_id": "rest_1",
    "name": "Crock Pot Chicken Baked Tacos",
    "description": "Put the uncooked chicken breasts in the crock pot. Pour the full bottle of salad dressing over the chicken. Sprinkle the rest of the ingredients over the top and mix them in a bit with a spoon.\r\nCover your crock pot with the lid and cook on",
    "price": 25.12,
    "ingredients": [
      "Chicken Breasts",
      "Vinaigrette Dressing",
      "Cumin",
      "Smoked Paprika",
      "Garlic",
      "Refried Beans",
      "Hard Taco Shells",
      "Shredded Mexican Cheese",
      "Grape Tomatoes",
      "Jalapeno",
      "Avocado",
      "Green Salsa",
      "Sour Cream",
      "Milk"
    ]
  },
  {
    "_id": "dish_17",
    "restaurant_id": "rest_1",
    "name": "Montreal Smoked Meat",
    "description": "To make the cure, in a small bowl mix together salt, pink salt, black pepper, coriander, sugar, bay leaf, and cloves. Coat entire brisket with the cure and place in an extra-large resealable plastic bag. Place in the coldest part of the ref",
    "price": 16.28,
    "ingredients": [
      "Beef Brisket",
      "Salt",
      "Black Pepper",
      "Coriander",
      "Sugar",
      "Bay Leaf",
      "Cloves",
      "Black Pepper",
      "Coriander",
      "Paprika",
      "Garlic",
      "Onion",
      "Dill",
      "English Mustard",
      "Celery Salt",
      "Red Pepper Flakes"
    ]
  },
  {
    "_id": "dish_18",
    "restaurant_id": "rest_1",
    "name": "Chocolate Caramel Crispy",
    "description": "Grease and line a 20 x 20cm/8\" x 8\" baking tin with parchment paper.\r\nPut the mars bars and butter in a heat proof bowl and place over a pan of barely simmering water. Mixing with a whisk, melt until the mixture is smooth.\r\nPour over the ri",
    "price": 26.33,
    "ingredients": [
      "Mars Bar",
      "Butter",
      "Rice Krispies",
      "Milk Chocolate"
    ]
  },
  {
    "_id": "dish_19",
    "restaurant_id": "rest_1",
    "name": "Soy-Glazed Meatloaves with Wasabi Mashed Potatoes & Roasted Carrots",
    "description": "1. Preheat oven to 425 degrees. Wash and dry all produce. Dice potatoes into 1/2-inch pieces. Trim, peel, and cut carrots on a diagonal into 1/2-inch-thick pieces. Trim and thinly slice scallions, separating whites from greens; finely chop ",
    "price": 17.26,
    "ingredients": [
      "Potatoes",
      "Carrots",
      "Scallions",
      "Garlic",
      "Bread",
      "Garlic Powder",
      "Soy Sauce",
      "Ground Beef",
      "Vegetable Oil",
      "Sugar",
      "Butter"
    ]
  },
  {
    "_id": "dish_20",
    "restaurant_id": "rest_1",
    "name": "Key Lime Pie",
    "description": "Heat the oven to 160C/fan 140C/gas 3. Whizz the biscuits to crumbs in a food processor (or put in a strong plastic bag and bash with a rolling pin). Mix with the melted butter and press into the base and up the sides of a 22cm loose-based t",
    "price": 24.15,
    "ingredients": [
      "Digestive Biscuits",
      "Butter",
      "Condensed Milk",
      "Egg Yolks",
      "Lime",
      "Double Cream",
      "Icing Sugar",
      "Lime"
    ]
  },
  {
    "_id": "dish_21",
    "restaurant_id": "rest_2",
    "name": "Chocolate Gateau",
    "description": "Preheat the oven to 180\u00b0C/350\u00b0F/Gas Mark 4. Grease and line the base of an 8 in round spring form cake tin with baking parchment\r\nBreak the chocolate into a heatproof bowl and place over a saucepan of gently simmering water and stir until i",
    "price": 23.7,
    "ingredients": [
      "Plain chocolate",
      "Butter",
      "Milk",
      "Eggs",
      "Granulated Sugar",
      "Flour"
    ]
  },
  {
    "_id": "dish_22",
    "restaurant_id": "rest_2",
    "name": "Garides Saganaki",
    "description": "Place the prawns in a pot and add enough water to cover. Boil for 5 minutes. Drain, reserving the liquid, and set aside.\r\nHeat 2 tablespoons of oil in a saucepan. Add the onion; cook and stir until soft. Mix in the parsley, wine, tomatoes, ",
    "price": 17.9,
    "ingredients": [
      "Raw king prawns",
      "Olive oil",
      "Chopped onion",
      "Freshly chopped parsley",
      "White wine",
      "Chopped tomatoes",
      "Minced garlic",
      "Cubed Feta cheese"
    ]
  },
  {
    "_id": "dish_23",
    "restaurant_id": "rest_2",
    "name": "Lasagna Sandwiches",
    "description": "1. In a small bowl, combine the first four ingredients; spread on four slices of bread. Layer with bacon, tomato and cheese; top with remaining bread.\r\n\r\n2. In a large skillet or griddle, melt 2 tablespoons butter. Toast sandwiches until li",
    "price": 6.36,
    "ingredients": [
      "Sour Cream",
      "Chopped Onion",
      "Dried Oregano",
      "Salt",
      "Bread",
      "Bacon",
      "Tomato",
      "Mozzarella",
      "Butter"
    ]
  },
  {
    "_id": "dish_24",
    "restaurant_id": "rest_2",
    "name": "Cevapi Sausages",
    "description": "Place the ground meat in a bowl. Chop the onion very finely and grate the garlic cloves. Add to the bowl. Add the chopped parsley, all sorts of paprika, baking soda, dried breadcrumbs, water, Vegeta, salt, and pepper.\r\nMix well with the han",
    "price": 26.1,
    "ingredients": [
      "Minced Beef",
      "Minced Pork",
      "Onion",
      "Garlic",
      "Parsley",
      "Paprika",
      "Baking Powder",
      "Breadcrumbs",
      "Water",
      "Vegetable Stock Cube",
      "Salt",
      "Pepper"
    ]
  },
  {
    "_id": "dish_25",
    "restaurant_id": "rest_2",
    "name": "Seri muka kuih",
    "description": "Soak glutinous rice with water for at least 1 \u00bd hours prior to using. Drain.\r\nPrepare a 9-inch round or square cake pan and spray with cooking spray or line with plastic wrap.\r\nMix coconut milk, water, salt and the rice. Pour it into cake p",
    "price": 13.09,
    "ingredients": [
      "Rice",
      "Coconut Milk",
      "Water",
      "Salt",
      "Corn Flour",
      "Flour",
      "Eggs",
      "Coconut Cream",
      "Sugar"
    ]
  },
  {
    "_id": "dish_26",
    "restaurant_id": "rest_2",
    "name": "Peach & Blueberry Grunt",
    "description": "Heat oven to 190C/170C fan/gas 5. Butter a wide shallow ovenproof dish. Blend the cornflour with the orange zest and juice, and put in a large pan with the sugar. Halve, stone and slice the peaches and add to the pan. Bring slowly to the bo",
    "price": 27.99,
    "ingredients": [
      "Corn Flour",
      "Orange",
      "Orange",
      "Caster Sugar",
      "Peaches",
      "Blueberries",
      "Self-raising Flour",
      "Butter",
      "Muscovado Sugar",
      "Cinnamon",
      "Milk"
    ]
  },
  {
    "_id": "dish_27",
    "restaurant_id": "rest_2",
    "name": "Rogaliki (Polish Croissant Cookies)",
    "description": "In a medium bowl mix egg yolks, philly cheese and baking powder using a hand held mixer. Carefully start adding the flour. When the mixture will not be mixing well, and will look like wood chips, put away the blending mixer and using your h",
    "price": 13.2,
    "ingredients": [
      "Butter",
      "Egg Yolks",
      "Cream Cheese",
      "Baking Powder",
      "Flour",
      "Jam"
    ]
  },
  {
    "_id": "dish_28",
    "restaurant_id": "rest_2",
    "name": "Beef Dumpling Stew",
    "description": "Preheat the oven to 180C/350F/Gas 4.\r\n\r\nFor the beef stew, heat the oil and butter in an ovenproof casserole and fry the beef until browned on all sides.\r\n\r\nSprinkle over the flour and cook for a further 2-3 minutes.\r\n\r\nAdd the garlic and a",
    "price": 16.86,
    "ingredients": [
      "Olive Oil",
      "Butter",
      "Beef",
      "Plain Flour",
      "Garlic",
      "Onions",
      "Celery",
      "Carrots",
      "Leek",
      "Swede",
      "Red Wine",
      "Beef Stock",
      "Bay Leaf",
      "Thyme",
      "Parsley",
      "Plain Flour",
      "Baking Powder",
      "Suet",
      "Water"
    ]
  },
  {
    "_id": "dish_29",
    "restaurant_id": "rest_2",
    "name": "Shrimp Chow Fun",
    "description": "STEP 1 - SOAK THE RICE NOODLES\r\nSoak the rice noodles overnight untill they are soft\r\nSTEP 2 - BOIL THE RICE NOODLES\r\nBoil the noodles for 10-15 minutes and then rinse with cold water to stop the cooking process of the noodles.\r\nSTEP 3 -MAR",
    "price": 26.68,
    "ingredients": [
      "Rice Stick Noodles",
      "Prawns",
      "Egg",
      "Pepper",
      "Sesame Seed Oil",
      "Cornstarch",
      "Oil",
      "Minced Garlic",
      "Ginger",
      "Onion",
      "Bean Sprouts",
      "Spring Onions",
      "Cooking wine",
      "Oyster Sauce",
      "Sugar",
      "Vinegar",
      "Soy Sauce"
    ]
  },
  {
    "_id": "dish_30",
    "restaurant_id": "rest_2",
    "name": "Shawarma",
    "description": "Combine the marinade ingredients in a large ziplock bag (or bowl).\r\nAdd the chicken and use your hands to make sure each piece is coated. If using a ziplock bag, I find it convenient to close the bag then massage the bag to disperse the rub",
    "price": 19.21,
    "ingredients": [
      "Chicken Thighs",
      "Coriander",
      "Cumin",
      "Cardamom",
      "Cayenne Pepper",
      "Paprika",
      "Lemon Juice",
      "Olive Oil",
      "Greek Yogurt",
      "Garlic Clove",
      "Cumin",
      "Lemon Juice",
      "Lettuce",
      "Tomato",
      "Pita Bread"
    ]
  },
  {
    "_id": "dish_31",
    "restaurant_id": "rest_2",
    "name": "Christmas Pudding Trifle",
    "description": "Peel the oranges using a sharp knife, ensuring all the pith is removed. Slice as thinly as possible and arrange over a dinner plate. Sprinkle with the demerara sugar followed by the Grand Marnier and set aside.\r\n\r\nCrumble the Christmas pudd",
    "price": 13.64,
    "ingredients": [
      "Orange",
      "Demerara Sugar",
      "Grand Marnier",
      "Christmas Pudding",
      "Custard",
      "Mascarpone",
      "Double Cream",
      "Flaked Almonds",
      "Dark Chocolate"
    ]
  },
  {
    "_id": "dish_32",
    "restaurant_id": "rest_2",
    "name": "Honey Teriyaki Salmon",
    "description": "Mix all the ingredients in the Honey Teriyaki Glaze together. Whisk to blend well. Combine the salmon and the Glaze together.\r\n\r\nHeat up a skillet on medium-low heat. Add the oil, Pan-fry the salmon on both sides until it\u2019s completely cooke",
    "price": 27.38,
    "ingredients": [
      "Salmon",
      "Olive oil",
      "Soy Sauce",
      "Sake",
      "Sesame Seed"
    ]
  },
  {
    "_id": "dish_33",
    "restaurant_id": "rest_2",
    "name": "Sweet and Sour Pork",
    "description": "Preparation\r\n1. Crack the egg into a bowl. Separate the egg white and yolk.\r\n\r\nSweet and Sour Pork\r\n2. Slice the pork tenderloin into strips.\r\n\r\n3. Prepare the marinade using a pinch of salt, one teaspoon of starch, two teaspoons of light s",
    "price": 23.33,
    "ingredients": [
      "Pork",
      "Egg",
      "Water",
      "Salt",
      "Sugar",
      "Soy Sauce",
      "Starch",
      "Tomato Puree",
      "Vinegar",
      "Coriander"
    ]
  },
  {
    "_id": "dish_34",
    "restaurant_id": "rest_2",
    "name": "Crispy Sausages and Greens",
    "description": "Preheat the oven to 350\u00b0. Remove the stems from one bunch of Tuscan kale and tear the leaves into 1\" pieces (mustard greens, collards, spinach, and chard are great, too). Coarsely chop half a head of green cabbage. Combine the greens in a l",
    "price": 24.07,
    "ingredients": [
      "Kale",
      "Italian Fennel Sausages",
      "Cabbage",
      "Garlic Clove",
      "Onion",
      "Shiitake Mushrooms",
      "Chicken Stock",
      "Salt",
      "Pepper"
    ]
  },
  {
    "_id": "dish_35",
    "restaurant_id": "rest_2",
    "name": "Bistek",
    "description": "0.\tMarinate beef in soy sauce, lemon (or calamansi), and ground black pepper for at least 1 hour. Note: marinate overnight for best result\r\n1.\tHeat the cooking oil in a pan then pan-fry half of the onions until the texture becomes soft. Set",
    "price": 10.35,
    "ingredients": [
      "Beef",
      "Soy Sauce",
      "Lemon",
      "Garlic",
      "Onion",
      "Olive Oil",
      "Water",
      "Salt"
    ]
  },
  {
    "_id": "dish_36",
    "restaurant_id": "rest_2",
    "name": "Duck Confit",
    "description": "The day before you want to make the dish, scatter half the salt, half the garlic and half of the herbs over the base of a small shallow dish. Lay the duck legs, skin-side up, on top, then scatter over the remaining salt, garlic and herbs. C",
    "price": 25.1,
    "ingredients": [
      "Sea Salt",
      "Bay Leaf",
      "Garlic",
      "Thyme",
      "Duck Legs",
      "White Wine"
    ]
  },
  {
    "_id": "dish_37",
    "restaurant_id": "rest_2",
    "name": "Vegetable Shepherds Pie",
    "description": "Add Ingredients:\r\n\r\n12 cups chopped mixed vegetables\r\n1   cup chopped fresh mushrooms \r\n1   cup pearl onions\r\n\r\nTOPPING:\r\n\r\nPreheat oven to 450\u00b0. Bake potatoes on a foil-lined baking sheet until tender, about 45 minutes. Let cool slightly, ",
    "price": 26.59,
    "ingredients": [
      "Potatoes",
      "Small Potatoes",
      "Salted Butter",
      "Mushrooms",
      "Brown Lentils",
      "Garlic",
      "Kosher Salt",
      "Onion",
      "Tomato Puree",
      "Bay Leaves",
      "Olive Oil",
      "Dry White Wine",
      "Vegetable Stock",
      "Cornstarch",
      "Soy Sauce",
      "Rosemary",
      "Parsley",
      "Sage",
      "Chives"
    ]
  },
  {
    "_id": "dish_38",
    "restaurant_id": "rest_2",
    "name": "Chicken Basquaise",
    "description": "Preheat the oven to 180\u00b0C/Gas mark 4. Have the chicken joints ready to cook. Heat the butter and 3 tbsp olive oil in a flameproof casserole or large frying pan. Brown the chicken pieces in batches on both sides, seasoning them with salt and",
    "price": 25.81,
    "ingredients": [
      "Chicken",
      "Butter",
      "Olive Oil",
      "Red Onions",
      "Red Pepper",
      "Chorizo",
      "Sun-Dried Tomatoes",
      "Garlic",
      "Basmati Rice",
      "Tomato Puree",
      "Paprika",
      "Bay Leaves",
      "Thyme",
      "Chicken Stock",
      "Dry White Wine",
      "Lemons",
      "Black Olives",
      "Salt",
      "Pepper"
    ]
  },
  {
    "_id": "dish_39",
    "restaurant_id": "rest_2",
    "name": "Three Fish Pie",
    "description": "Preheat the oven to 200C/400F/Gas 6 (180C fan).\r\nPut the potatoes into a saucepan of cold salted water. Bring up to the boil and simmer until completely tender. Drain well and then mash with the butter and milk. Add pepper and taste to chec",
    "price": 16.2,
    "ingredients": [
      "Potatoes",
      "Butter",
      "Milk",
      "Gruyere",
      "Butter",
      "Leek",
      "Plain Flour",
      "White Wine",
      "Milk",
      "Parsley",
      "Salmon",
      "Haddock",
      "Smoked Haddock",
      "Eggs"
    ]
  },
  {
    "_id": "dish_40",
    "restaurant_id": "rest_2",
    "name": "Fish Soup (Ukha)",
    "description": "In a medium pot, heat the olive oil over medium-high heat. Add the onions and cook, stirring occasionally until the onions start to caramelize. Add the carrots and cook until the carrots start to soften, about 4 more minutes.\r\nAdd the stock",
    "price": 20.36,
    "ingredients": [
      "Olive Oil",
      "Onion",
      "Carrots",
      "Fish Stock",
      "Water",
      "Potatoes",
      "Bay Leaf",
      "Cod",
      "Salmon"
    ]
  },
  {
    "_id": "dish_41",
    "restaurant_id": "rest_3",
    "name": "Portuguese prego with green piri-piri",
    "description": "STEP 1\r\n\r\nRub the garlic over the steaks then put in a sandwich bag and tip in the olive oil, sherry vinegar and parsley stalks. Smoosh everything together, then use a rolling pin to bash the steaks a few times. Leave for 1-2 hours.\r\n\r\nSTEP",
    "price": 14.58,
    "ingredients": [
      "Garlic",
      "Beef Fillet",
      "Olive Oil",
      "Vinegar",
      "Parsley",
      "Ciabatta",
      "Rocket",
      "Basil Leaves",
      "Parsley",
      "Jalapeno",
      "Vinegar",
      "Spring Onions",
      "Garlic",
      "Caster Sugar"
    ]
  },
  {
    "_id": "dish_42",
    "restaurant_id": "rest_3",
    "name": "Baba Ghanoush",
    "description": "Preheat an outdoor grill for medium-high heat and lightly oil the grate. Prick the surface of the skin of eggplants several times with the tip of a knife.\r\n\r\nPlace eggplants directly on grill. Turn frequently with tongs while skin chars. Co",
    "price": 13.32,
    "ingredients": [
      "Egg Plants",
      "Garlic",
      "Kosher Salt",
      "Lemon",
      "Tahini",
      "Extra Virgin Olive Oil",
      "Greek Yogurt",
      "Cayenne Pepper",
      "Mint",
      "Parsley"
    ]
  },
  {
    "_id": "dish_43",
    "restaurant_id": "rest_3",
    "name": "Salmon Avocado Salad",
    "description": "Season the salmon, then rub with oil. Mix the dressing ingredients together. Halve, stone, peel and slice the avocados. Halve and quarter the cucumber lengthways, then cut into slices. Divide salad, avocado and cucumber between four plates,",
    "price": 7.9,
    "ingredients": [
      "Salmon",
      "Avocado",
      "Cucumber",
      "Spinach",
      "Mint",
      "Lime",
      "Honey",
      "Olive Oil"
    ]
  },
  {
    "_id": "dish_44",
    "restaurant_id": "rest_3",
    "name": "Carrot Cake",
    "description": "For the carrot cake, preheat the oven to 160C/325F/Gas 3. Grease and line a 26cm/10in springform cake tin.\r\nMix all of the ingredients for the carrot cake, except the carrots and walnuts, together in a bowl until well combined. Stir in the ",
    "price": 13.26,
    "ingredients": [
      "Vegetable Oil",
      "Plain Flour",
      "Bicarbonate Of Soda",
      "Sugar",
      "Eggs",
      "Salt",
      "Cinnamon",
      "Carrots",
      "Walnuts",
      "Cream Cheese",
      "Caster Sugar",
      "Butter"
    ]
  },
  {
    "_id": "dish_45",
    "restaurant_id": "rest_3",
    "name": "Tunisian Lamb Soup",
    "description": "Add the lamb to a casserole and cook over high heat. When browned, remove from the heat and set aside.\r\nKeep a tablespoon of fat in the casserole and discard the rest. Reduce to medium heat then add the garlic, onion and spinach and cook un",
    "price": 15.42,
    "ingredients": [
      "Lamb Mince",
      "Garlic",
      "Onion",
      "Spinach",
      "Tomato Puree",
      "Cumin",
      "Chicken Stock",
      "Harissa Spice",
      "Chickpeas",
      "Lemon Juice",
      "Macaroni",
      "Salt",
      "Pepper"
    ]
  },
  {
    "_id": "dish_46",
    "restaurant_id": "rest_3",
    "name": "Crispy Eggplant",
    "description": "Slice eggplant into 1 cm (0.4-inch) slices. Place them in a bowl and sprinkle them with salt. allow them to sit for 30 minutes to render some of their liquid and bitterness.\r\n2. After 30 minutes wash eggplant slices from salt and pat dry wi",
    "price": 14.21,
    "ingredients": [
      "Egg Plants",
      "Breadcrumbs",
      "Sesame Seed",
      "Eggs",
      "Salt",
      "Pepper",
      "Vegetable Oil"
    ]
  },
  {
    "_id": "dish_47",
    "restaurant_id": "rest_3",
    "name": "Beef Mechado",
    "description": "0.\tMake the beef tenderloin marinade by combining soy sauce, vinegar, ginger, garlic, sesame oil, olive oil, sugar, salt, and ground black pepper in a large bowl. Mix well.\r\n1.\tAdd the cubed beef tenderloin to the bowl with the beef tenderl",
    "price": 18.67,
    "ingredients": [
      "Garlic",
      "Onion",
      "Beef",
      "Tomato Puree",
      "Water",
      "Olive Oil",
      "Lemon",
      "Potatoes",
      "Soy Sauce",
      "Black Pepper",
      "Bay Leaves",
      "Salt"
    ]
  },
  {
    "_id": "dish_48",
    "restaurant_id": "rest_3",
    "name": "Moussaka",
    "description": "Heat the grill to high. Brown the beef in a deep ovenproof frying pan over a high heat for 5 mins. Meanwhile, prick the aubergine with a fork, then microwave on High for 3-5 mins until soft. Mix the yogurt, egg and parmesan together, then a",
    "price": 6.03,
    "ingredients": [
      "Beef",
      "Aubergine",
      "Greek Yogurt",
      "Egg",
      "Parmesan",
      "Tomato",
      "Tomato Puree",
      "Potatoes"
    ]
  },
  {
    "_id": "dish_49",
    "restaurant_id": "rest_3",
    "name": "Tonkatsu pork",
    "description": "STEP 1\r\nRemove the large piece of fat on the edge of each pork loin, then bash each of the loins between two pieces of baking parchment until around 1cm in thickness \u2013 you can do this using a meat tenderiser or a rolling pin. Once bashed, u",
    "price": 9.67,
    "ingredients": [
      "Pork Chops",
      "Flour",
      "Eggs",
      "Breadcrumbs",
      "Vegetable Oil",
      "Tomato Ketchup",
      "Worcestershire Sauce",
      "Oyster Sauce",
      "Caster Sugar"
    ]
  },
  {
    "_id": "dish_50",
    "restaurant_id": "rest_3",
    "name": "Spaghetti alla Carbonara",
    "description": "STEP 1\r\nPut a large saucepan of water on to boil.\r\n\r\nSTEP 2\r\nFinely chop the 100g pancetta, having first removed any rind. Finely grate 50g pecorino cheese and 50g parmesan and mix them together.\r\n\r\nSTEP 3\r\nBeat the 3 large eggs in a medium",
    "price": 8.83,
    "ingredients": [
      "Spaghetti",
      "Egg Yolks",
      "Salt",
      "Bacon",
      "Pecorino",
      "Black Pepper"
    ]
  },
  {
    "_id": "dish_51",
    "restaurant_id": "rest_3",
    "name": "Spotted Dick",
    "description": "Put the flour and salt in a bowl. Add the suet, currants, sugar, lemon and orange zest.\r\nPour in 150ml milk and mix to a firm but moist dough, adding the extra milk if necessary.\r\nShape into a fat roll about 20cm long. Place on a large rect",
    "price": 11.96,
    "ingredients": [
      "Self-raising Flour",
      "Salt",
      "Suet",
      "Currants",
      "Caster Sugar",
      "Lemon",
      "Orange",
      "Milk",
      "Custard"
    ]
  },
  {
    "_id": "dish_52",
    "restaurant_id": "rest_3",
    "name": "Garides Saganaki",
    "description": "Place the prawns in a pot and add enough water to cover. Boil for 5 minutes. Drain, reserving the liquid, and set aside.\r\nHeat 2 tablespoons of oil in a saucepan. Add the onion; cook and stir until soft. Mix in the parsley, wine, tomatoes, ",
    "price": 11.82,
    "ingredients": [
      "Raw king prawns",
      "Olive oil",
      "Chopped onion",
      "Freshly chopped parsley",
      "White wine",
      "Chopped tomatoes",
      "Minced garlic",
      "Cubed Feta cheese"
    ]
  },
  {
    "_id": "dish_53",
    "restaurant_id": "rest_3",
    "name": "Tunisian Lamb Soup",
    "description": "Add the lamb to a casserole and cook over high heat. When browned, remove from the heat and set aside.\r\nKeep a tablespoon of fat in the casserole and discard the rest. Reduce to medium heat then add the garlic, onion and spinach and cook un",
    "price": 10.88,
    "ingredients": [
      "Lamb Mince",
      "Garlic",
      "Onion",
      "Spinach",
      "Tomato Puree",
      "Cumin",
      "Chicken Stock",
      "Harissa Spice",
      "Chickpeas",
      "Lemon Juice",
      "Macaroni",
      "Salt",
      "Pepper"
    ]
  },
  {
    "_id": "dish_54",
    "restaurant_id": "rest_3",
    "name": "Flamiche",
    "description": "For the pastry, sift the flour and salt into the bowl of a food processor, add the butter and lard, then whizz together briefly until the mixture looks like fine breadcrumbs. Tip the mixture into a bowl, then stir in the cheese and enough o",
    "price": 22.4,
    "ingredients": [
      "Butter",
      "Leek",
      "Salt",
      "Creme Fraiche",
      "Egg",
      "Egg Yolks",
      "Nutmeg",
      "Plain Flour",
      "Salt",
      "Butter",
      "Lard",
      "Cheddar Cheese",
      "Water"
    ]
  },
  {
    "_id": "dish_55",
    "restaurant_id": "rest_3",
    "name": "Beef Lo Mein",
    "description": "STEP 1 - MARINATING THE BEEF\r\nIn a bowl, add the beef, salt, 1 pinch white pepper, 1 Teaspoon sesame seed oil, 1/2 egg, corn starch,1 Tablespoon of oil and mix together.\r\nSTEP 2 - BOILING THE THE NOODLES\r\nIn a 6 qt pot add your noodles to b",
    "price": 26.42,
    "ingredients": [
      "Beef",
      "Salt",
      "Pepper",
      "Sesame Seed Oil",
      "Egg",
      "Starch",
      "Oil",
      "Noodles",
      "Onion",
      "Minced Garlic",
      "Ginger",
      "Bean Sprouts",
      "Mushrooms",
      "Water",
      "Oyster Sauce",
      "Sugar",
      "Soy Sauce"
    ]
  },
  {
    "_id": "dish_56",
    "restaurant_id": "rest_3",
    "name": "Apple Frangipan Tart",
    "description": "Preheat the oven to 200C/180C Fan/Gas 6.\r\nPut the biscuits in a large re-sealable freezer bag and bash with a rolling pin into fine crumbs. Melt the butter in a small pan, then add the biscuit crumbs and stir until coated with butter. Tip i",
    "price": 15.79,
    "ingredients": [
      "digestive biscuits",
      "butter",
      "Bramley apples",
      "Salted Butter",
      "caster sugar",
      "free-range eggs, beaten",
      "ground almonds",
      "almond extract",
      "flaked almonds"
    ]
  },
  {
    "_id": "dish_57",
    "restaurant_id": "rest_3",
    "name": "Chicken Karaage",
    "description": "Add the ginger, garlic, soy sauce, sake and sugar to a bowl and whisk to combine. Add the chicken, then stir to coat evenly. Cover and refrigerate for at least 1 hour.\r\n\r\nAdd 1 inch of vegetable oil to a heavy bottomed pot and heat until th",
    "price": 10.81,
    "ingredients": [
      "Chicken",
      "Ginger",
      "Garlic",
      "Soy sauce",
      "Sake",
      "Granulated sugar",
      "Potato starch",
      "Vegetable oil",
      "Lemon"
    ]
  },
  {
    "_id": "dish_58",
    "restaurant_id": "rest_3",
    "name": "Saltfish and Ackee",
    "description": "For the saltfish, soak the salt cod overnight, changing the water a couple of times.\r\nDrain, then put the cod in a large pan of fresh water and bring to the boil. Drain again, add fresh water and bring to the boil again.\r\nSimmer for about f",
    "price": 20.55,
    "ingredients": [
      "Salt Cod",
      "Ackee",
      "Onion",
      "Paprika",
      "Curry Powder",
      "Jerusalem Artichokes",
      "Hotsauce",
      "Red Pepper",
      "Yellow Pepper",
      "Tomatoes",
      "Salt",
      "Pepper",
      "Self-raising Flour",
      "Suet",
      "Salt",
      "Olive Oil"
    ]
  },
  {
    "_id": "dish_59",
    "restaurant_id": "rest_3",
    "name": "Lamb Rogan josh",
    "description": "\r\nPut the onions in a food processor and whizz until very finely chopped. Heat the oil in a large heavy-based pan, then fry the onion with the lid on, stirring every now and then, until it is really golden and soft. Add the garlic and ginge",
    "price": 26.9,
    "ingredients": [
      "Onion",
      "Sunflower Oil",
      "Garlic",
      "Ginger",
      "Madras Paste",
      "Paprika",
      "cinnamon stick",
      "Cardamom",
      "Cloves",
      "Bay Leaf",
      "Tomato Pur\u00e9e",
      "Lamb",
      "Greek yogurt",
      "Coriander"
    ]
  },
  {
    "_id": "dish_60",
    "restaurant_id": "rest_3",
    "name": "Toad In The Hole",
    "description": "Preheat the oven to 200\u00b0C/fan180\u00b0C/gas 6. fry sausages in a non-stick pan until browned.\r\nDrizzle vegetable oil in a 30cm x 25cm x 6cm deep roasting tray and heat in the oven for 5 minutes.\r\nPut the plain flour in a bowl, crack in the mediu",
    "price": 6.48,
    "ingredients": [
      "sausages",
      "vegetable oil",
      "plain flour",
      "eggs",
      "horseradish",
      "milk",
      "cherry tomatoes"
    ]
  }
]